nercone_modern/__init__.py
nercone_modern/__main__.py
nercone_modern/color.py
nercone_modern/logging.py
nercone_modern/progressbar.py
nercone_modern/text.py
nercone_modern-1.9.1.dist-info/WHEEL
nercone_modern-1.9.1.dist-info/METADATA
nercone_modern-1.9.1.dist-info/RECORD
