Metadata-Version: 2.3
Name: nercone-modern
Version: 1.9.1
Summary: Modern CLI Library
Author: Nercone
Author-email: Nercone <nercone@diamondgotcat.net>
License: MIT
Classifier: Programming Language :: Python :: 3
Classifier: License :: OSI Approved :: MIT License
Classifier: Operating System :: OS Independent
Requires-Python: >=3.6
Project-URL: Homepage, https://github.com/DiamondGotCat/nercone-modern
